LICENSE.txt
MANIFEST.in
README.rst
setup.py
contrib/__init__.py
contrib/actorize.py
contrib/websocket.py
doc/design-routing.org
doc/design.org
doc/developer.org
doc/gen_all.sh
doc/gen_html.sh
doc/gen_pdf.sh
doc/gen_text.sh
doc/in_depth.org
doc/index.org
doc/releases.org
doc/thespian.cls
doc/thespian.css
doc/thespian.el
doc/thesplogo2.jpg
doc/thesplogo2.png
doc/using.org
examples/hellogoodbye.py
examples/logsetup.py
examples/socketstress.py
examples/fibtroupe/README.org
examples/fibtroupe/fibactor.py
examples/fibtroupe/timer.py
examples/httpserver/common.py
examples/httpserver/http_server1.py
examples/httpserver/http_server2.py
examples/multi_system/README.org
examples/multi_system/act1/README.org
examples/multi_system/act1/app.py
examples/multi_system/act1/encoder.py
examples/multi_system/act1/morse.py
examples/multi_system/act1/start.py
examples/multi_system/act1/stop.py
examples/multi_system/act2/README.org
examples/multi_system/act2/app.py
examples/multi_system/act2/diff_from_prev.sh
examples/multi_system/act2/encoder.py
examples/multi_system/act2/morse.py
examples/multi_system/act2/start.py
examples/multi_system/act2/stop.py
examples/multi_system/act3/README.org
examples/multi_system/act3/app.py
examples/multi_system/act3/diff_from_prev.sh
examples/multi_system/act3/encoder.py
examples/multi_system/act3/morse.py
examples/multi_system/act3/start.py
examples/multi_system/act3/stop.py
examples/multi_system/act4/README.org
examples/multi_system/act4/app.py
examples/multi_system/act4/diff_from_prev.sh
examples/multi_system/act4/encoder.py
examples/multi_system/act4/morse.py
examples/multi_system/act4/start.py
examples/multi_system/act4/stop.py
examples/multi_system/act5/README.org
examples/multi_system/act5/app.py
examples/multi_system/act5/chgcap.py
examples/multi_system/act5/diff_from_prev.sh
examples/multi_system/act5/encoder.py
examples/multi_system/act5/morse.py
examples/multi_system/act5/start.py
examples/multi_system/act5/stop.py
thespian.egg-info/PKG-INFO
thespian.egg-info/SOURCES.txt
thespian.egg-info/dependency_links.txt
thespian.egg-info/top_level.txt
